routeparser/__init__.py
routeparser-0.1.0.dist-info/COPYING
routeparser-0.1.0.dist-info/COPYING.LESSER
routeparser-0.1.0.dist-info/LICENSE
routeparser-0.1.0.dist-info/METADATA
routeparser-0.1.0.dist-info/WHEEL
routeparser-0.1.0.dist-info/top_level.txt
routeparser-0.1.0.dist-info/RECORD
